transunet/__init__.py
transunet/decoder_layers.py
transunet/encoder_layers.py
transunet/model.py
transunet/resnet_v2.py
transunet/utils.py
transunet/version.py
transunet-1.0.3.dist-info/LICENSE.md
transunet-1.0.3.dist-info/METADATA
transunet-1.0.3.dist-info/WHEEL
transunet-1.0.3.dist-info/top_level.txt
transunet-1.0.3.dist-info/RECORD
