Metadata-Version: 2.1
Name: transunet
Version: 1.0.3
Summary: Tensorflow Extra Utilities. https://github.com/awsaf49/TransUNet-tf
Home-page: https://github.com/awsaf49/TransUNet-tf
Author: Awsaf
Author-email: awsaf49@gmail.com
License: MIT
Keywords: tensorflow TransUNet
Platform: UNKNOWN
Classifier: Development Status :: 3 - Alpha
Classifier: Intended Audience :: Developers
Classifier: Intended Audience :: Science/Research
Classifier: License :: OSI Approved :: Apache Software License
Classifier: Programming Language :: Python :: 3.6
Classifier: Programming Language :: Python :: 3.7
Classifier: Programming Language :: Python :: 3.8
Classifier: Topic :: Scientific/Engineering
Classifier: Topic :: Scientific/Engineering :: Artificial Intelligence
Classifier: Topic :: Software Development
Classifier: Topic :: Software Development :: Libraries
Classifier: Topic :: Software Development :: Libraries :: Python Modules
Requires-Python: >=3.6
License-File: LICENSE.md
Requires-Dist: tensorflow-addons
Requires-Dist: validators
Requires-Dist: tensorflow
